popclass/__init__.py
popclass/classify.py
popclass/model.py
popclass/posterior.py
popclass/uq.py
popclass/visualization.py
popclass/data/popsycle_singles_raithel18.asdf
popclass/data/popsycle_singles_spera15.asdf
popclass/data/popsycle_singles_sukhboldn20.asdf
popclass-0.2.0.dist-info/METADATA
popclass-0.2.0.dist-info/WHEEL
popclass-0.2.0.dist-info/licenses/LICENSE
popclass-0.2.0.dist-info/licenses/NOTICE
popclass-0.2.0.dist-info/RECORD
