Metadata-Version: 2.3
Name: popclass
Version: 0.2.0
Summary: A python package that allows flexable, probabilistic classification of a microlensing event
Project-URL: Homepage, https://github.com/llnl/popclass
Project-URL: Documentation, https://popclass.readthedocs.io
Project-URL: Repository, https://github.com/llnl/popclass
Project-URL: Issues, https://github.com/llnl/popclass/issues
Project-URL: Changelog, https://github.com/LLNL/popclass/releases
Author-email: "Greg Sallaberry, Scott E. Perkins, Peter McGill, Zofia Kaczmarek, William A. Dawson" <mcgill5@llnl.gov>
License: MIT
License-File: LICENSE
License-File: NOTICE
Classifier: Intended Audience :: Science/Research
Classifier: License :: OSI Approved :: MIT License
Classifier: Operating System :: OS Independent
Classifier: Programming Language :: Python
Classifier: Programming Language :: Python :: 3
Requires-Python: >=3.8
Requires-Dist: asdf
Requires-Dist: matplotlib
Requires-Dist: numpy
Requires-Dist: scikit-learn
Requires-Dist: scipy
Provides-Extra: docs
Requires-Dist: sphinx; extra == 'docs'
Requires-Dist: sphinx-rtd-theme; extra == 'docs'
Requires-Dist: sphinxcontrib-bibtex; extra == 'docs'
Provides-Extra: test
Requires-Dist: arviz; extra == 'test'
Requires-Dist: dynesty; extra == 'test'
Requires-Dist: pytest; extra == 'test'
